DESCRIPTION
LICENSE
MANIFEST.in
README.md
RELEASE.rst
requirements.txt
setup.cfg
setup.py
tox.ini
open_discussions_api/__init__.py
open_discussions_api/base.py
open_discussions_api/base_test.py
open_discussions_api/betamax_config.py
open_discussions_api/client.py
open_discussions_api/client_test.py
open_discussions_api/conftest.py
open_discussions_api/constants.py
open_discussions_api/recorder.py
open_discussions_api/utils.py
open_discussions_api/utils_test.py
open_discussions_api/channels/__init__.py
open_discussions_api/channels/client.py
open_discussions_api/channels/client_test.py
open_discussions_api/channels/constants.py
open_discussions_api/users/__init__.py
open_discussions_api/users/client.py
open_discussions_api/users/client_test.py
open_discussions_client.egg-info/PKG-INFO
open_discussions_client.egg-info/SOURCES.txt
open_discussions_client.egg-info/dependency_links.txt
open_discussions_client.egg-info/requires.txt
open_discussions_client.egg-info/top_level.txt