Metadata-Version: 1.0
Name: open-discussions-client
Version: 0.4.0
Summary: Client for mitodl/open-discussions
